netauth/__init__.py
netauth/_kv.py
netauth/_types.py
netauth/cache.py
netauth/error.py
netauth/py.typed
netauth/v2.py
netauth/_pb/__init__.py
netauth/_pb/netauth_pb2.py
netauth/_pb/netauth_pb2.pyi
netauth/_pb/netauth_pb2_grpc.py
netauth/_pb/v2/__init__.py
netauth/_pb/v2/rpc_pb2.py
netauth/_pb/v2/rpc_pb2.pyi
netauth/_pb/v2/rpc_pb2_grpc.py
netauth-0.1.0.dist-info/LICENSE
netauth-0.1.0.dist-info/METADATA
netauth-0.1.0.dist-info/WHEEL
netauth-0.1.0.dist-info/top_level.txt
netauth-0.1.0.dist-info/RECORD
