Metadata-Version: 2.1
Name: netauth
Version: 0.1.0
Summary: NetAuth client library
Author-email: classabbyamp <dev@placeviolette.net>
Project-URL: Homepage, https://netauth.org
Project-URL: Documentation, https://python.netauth.org
Project-URL: Repository, https://github.com/netauth/netauth-python
Project-URL: Changelog, https://github.com/netauth/netauth-python/blob/master/CHANGELOG.md
Keywords: secure-access,authentication-service,netauth
Classifier: License :: OSI Approved :: MIT License
Classifier: Programming Language :: Python :: 3
Classifier: Programming Language :: Python :: 3.11
Classifier: Programming Language :: Python :: 3.12
Requires-Python: >=3.11
License-File: LICENSE
Requires-Dist: grpcio
Requires-Dist: protobuf
Provides-Extra: ci
Requires-Dist: ruff ; extra == 'ci'
Provides-Extra: dev
Requires-Dist: grpcio-tools ; extra == 'dev'
Provides-Extra: docs
Requires-Dist: sphinx ; extra == 'docs'
Requires-Dist: sphinx-rtd-theme ; extra == 'docs'
Requires-Dist: sphinx-toolbox ; extra == 'docs'
Requires-Dist: sphinx-autodoc-typehints ; extra == 'docs'
Requires-Dist: enum-tools ; extra == 'docs'
Provides-Extra: publish
Requires-Dist: build ; extra == 'publish'
Requires-Dist: twine ; extra == 'publish'
Provides-Extra: test
Requires-Dist: pytest ; extra == 'test'
